evaluator/__init__.py
evaluator/evaluator.py
evaluator/utils.py
e_valuator-0.1.0.dist-info/METADATA
e_valuator-0.1.0.dist-info/WHEEL
e_valuator-0.1.0.dist-info/top_level.txt
e_valuator-0.1.0.dist-info/RECORD
