Metadata-Version: 2.4
Name: e-valuator
Version: 0.1.0
Summary: Sequential evaluator for LLM trajectories
Author: Shuvom Sadhuka
License: MIT
Project-URL: Homepage, https://github.com/shuvom-s/e-valuator
Project-URL: Repository, https://github.com/shuvom-s/e-valuator
Requires-Python: >=3.9
Requires-Dist: numpy
Requires-Dist: pandas
Requires-Dist: scikit-learn
Requires-Dist: scipy
Requires-Dist: tqdm
Provides-Extra: dev
Requires-Dist: pytest; extra == "dev"
